extra_streamlit_components/__init__.py
extra_streamlit_components/BouncingImage/__init__.py
extra_streamlit_components/CookieManager/__init__.py
extra_streamlit_components/Router/__init__.py
extra_streamlit_components/StepperBar/__init__.py
extra_streamlit_components/TabBar/__init__.py
extra_streamlit_components_SEM-0.1.55.dist-info/LICENSE
extra_streamlit_components_SEM-0.1.55.dist-info/METADATA
extra_streamlit_components_SEM-0.1.55.dist-info/WHEEL
extra_streamlit_components_SEM-0.1.55.dist-info/top_level.txt
extra_streamlit_components_SEM-0.1.55.dist-info/RECORD
